setup.py
scripts/rsyncbenri
scripts/sshbenri
sshbenri/__init__.py
sshbenri/compat.py
sshbenri/core.py
sshbenri/rsyncbenri.py
sshbenri/sshbenri.py
sshbenri.egg-info/PKG-INFO
sshbenri.egg-info/SOURCES.txt
sshbenri.egg-info/dependency_links.txt
sshbenri.egg-info/top_level.txt