Metadata-Version: 1.0
Name: sshbenri
Version: 0.0.7
Summary: ssh benri script
Home-page: UNKNOWN
Author: UNKNOWN
Author-email: UNKNOWN
License: UNKNOWN
Platform: UNKNOWN
